pytorch/__init__.py
pytorch/base_wrapper.py
pytorch/classification_wrapper.py
pytorch/compiler.py
pytorch/detection_wrapper.py
pytorch/regression_wrapper.py
pytorch/segmentation_wrapper.py
sklearn/__init__.py
training_kit-0.1.1.dist-info/METADATA
training_kit-0.1.1.dist-info/WHEEL
training_kit-0.1.1.dist-info/top_level.txt
training_kit-0.1.1.dist-info/RECORD
